askui_runner/__init__.py
askui_runner/__main__.py
askui_runner/agent_app.py
askui_runner/config.py
askui_runner/logging.py
askui_runner/modules/__init__.py
askui_runner/modules/agents/__init__.py
askui_runner/modules/agents/config.py
askui_runner/modules/agents/containers.py
askui_runner/modules/agents/file_service.py
askui_runner/modules/core/__init__.py
askui_runner/modules/core/config.py
askui_runner/modules/core/containers.py
askui_runner/modules/core/models.py
askui_runner/modules/core/runner.py
askui_runner/modules/core/infrastructure/__init__.py
askui_runner/modules/core/infrastructure/askui.py
askui_runner/modules/core/infrastructure/agent/__init__.py
askui_runner/modules/core/infrastructure/files/__init__.py
askui_runner/modules/core/infrastructure/files/askui.py
askui_runner/modules/core/infrastructure/files/files.py
askui_runner/modules/core/infrastructure/files/retry_utils.py
askui_runner/modules/core/infrastructure/files/utils.py
askui_runner/modules/core/infrastructure/results_upload/__init__.py
askui_runner/modules/core/infrastructure/results_upload/askui.py
askui_runner/modules/core/infrastructure/runner/__init__.py
askui_runner/modules/core/infrastructure/runner/askui.py
askui_runner/modules/core/infrastructure/workflows_download/__init__.py
askui_runner/modules/core/infrastructure/workflows_download/askui.py
askui_runner/modules/queue/__init__.py
askui_runner/modules/queue/config.py
askui_runner/modules/queue/containers.py
askui_runner/modules/queue/models.py
askui_runner/modules/queue/queue.py
askui_runner/modules/queue/infrastructure/__init__.py
askui_runner/modules/queue/infrastructure/clock/__init__.py
askui_runner/modules/queue/infrastructure/clock/time.py
askui_runner/modules/queue/infrastructure/runner/__init__.py
askui_runner/modules/queue/infrastructure/runner/k8s_job.py
askui_runner/modules/queue/infrastructure/runner/shared.py
askui_runner/modules/queue/infrastructure/runner/subprocess.py
askui_runner-0.3.1.dist-info/LICENSE
askui_runner-0.3.1.dist-info/METADATA
askui_runner-0.3.1.dist-info/WHEEL
askui_runner-0.3.1.dist-info/top_level.txt
askui_runner-0.3.1.dist-info/RECORD
