Metadata-Version: 2.2
Name: askui-runner
Version: 0.3.1
Summary: Runner for Workflows Defined in AskUI Studio
License: UNLICENSED
Requires-Python: >=3.10
License-File: LICENSE
Requires-Dist: pydantic>=2.10.4
Requires-Dist: jinja2>=3.1.4
Requires-Dist: requests>=2.32.3
Requires-Dist: tenacity>=9.0.0
Requires-Dist: requests-toolbelt>=1.0.0
Requires-Dist: pyyaml>=6.0.2
Requires-Dist: typer[all]>=0.15.1
Requires-Dist: kubernetes>=28.0.0
Requires-Dist: pydantic-settings>=2.7.0
